[
    {
        "name": "Recipe 1",
        "date": "2024-01-01",
        "image": "path_to_image_1.jpg",
        "shortDescription": "This is a short description of Recipe 1.",
        "ingredients": ["Ingredient 1", "Ingredient 2"],
        "instructions": "Instructions for Recipe 1."
    },
    {
        "name": "Recipe 2",
        "date": "2024-01-02",
        "image": "path_to_image_2.jpg",
        "shortDescription": "This is a short description of Recipe 2.",
        "ingredients": ["Ingredient 1", "Ingredient 2"],
        "instructions": "Instructions for Recipe 2."
    }
    // Add more recipes as needed
]
